MANIFEST.in
README.rst
README.txt
setup.py
docs/CREDITS.txt
docs/HISTORY.txt
docs/INSTALL.txt
docs/LICENSE.GPL
docs/LICENSE.txt
docs/tango-star-README
docs/tango-star.svg
src/sc/__init__.py
src/sc.social.bookmarks.egg-info/PKG-INFO
src/sc.social.bookmarks.egg-info/SOURCES.txt
src/sc.social.bookmarks.egg-info/dependency_links.txt
src/sc.social.bookmarks.egg-info/entry_points.txt
src/sc.social.bookmarks.egg-info/namespace_packages.txt
src/sc.social.bookmarks.egg-info/not-zip-safe
src/sc.social.bookmarks.egg-info/pbr.json
src/sc.social.bookmarks.egg-info/requires.txt
src/sc.social.bookmarks.egg-info/top_level.txt
src/sc/social/__init__.py
src/sc/social/bookmarks/__init__.py
src/sc/social/bookmarks/config.py
src/sc/social/bookmarks/configure.zcml
src/sc/social/bookmarks/profiles.zcml
src/sc/social/bookmarks/setuphandlers.py
src/sc/social/bookmarks/testing.py
src/sc/social/bookmarks/vocabularies.py
src/sc/social/bookmarks/Extensions/Install.py
src/sc/social/bookmarks/Extensions/__init__.py
src/sc/social/bookmarks/browser/__init__.py
src/sc/social/bookmarks/browser/common.py
src/sc/social/bookmarks/browser/configure.zcml
src/sc/social/bookmarks/browser/interfaces.py
src/sc/social/bookmarks/browser/portlet.py
src/sc/social/bookmarks/browser/sb_images/blinkbits.png
src/sc/social/bookmarks/browser/sb_images/blinklist.png
src/sc/social/bookmarks/browser/sb_images/blogmarks.png
src/sc/social/bookmarks/browser/sb_images/blogmemes.png
src/sc/social/bookmarks/browser/sb_images/blogter.png
src/sc/social/bookmarks/browser/sb_images/bluedot.png
src/sc/social/bookmarks/browser/sb_images/bookmarkhu.png
src/sc/social/bookmarks/browser/sb_images/bumpzee.png
src/sc/social/bookmarks/browser/sb_images/co.mments.gif
src/sc/social/bookmarks/browser/sb_images/connotea.png
src/sc/social/bookmarks/browser/sb_images/delicious.png
src/sc/social/bookmarks/browser/sb_images/delirious.png
src/sc/social/bookmarks/browser/sb_images/digg.png
src/sc/social/bookmarks/browser/sb_images/dotnetkicks.png
src/sc/social/bookmarks/browser/sb_images/dzone.png
src/sc/social/bookmarks/browser/sb_images/facebook.jpg
src/sc/social/bookmarks/browser/sb_images/fark.png
src/sc/social/bookmarks/browser/sb_images/feedmelinks.png
src/sc/social/bookmarks/browser/sb_images/fleck.gif
src/sc/social/bookmarks/browser/sb_images/furl.png
src/sc/social/bookmarks/browser/sb_images/google.jpg
src/sc/social/bookmarks/browser/sb_images/gwar.gif
