Metadata-Version: 1.1
Name: sc.social.bookmarks
Version: 1.3.2
Summary: Add social bookmarking and sharing capabilities to a
Home-page: http://www.simplesconsultoria.com.br/
Author: Simples Consultoria
Author-email: products@simplesconsultoria.com.br
License: GPL
Keywords: plone web social bookmarks delicious digg
Platform: UNKNOWN
Classifier: Development Status :: 5 - Production/Stable
Classifier: Environment :: Web Environment
Classifier: Framework :: Plone
Classifier: Framework :: Plone :: 4.1
Classifier: Framework :: Plone :: 4.2
Classifier: Framework :: Plone :: 4.3
Classifier: Intended Audience :: Developers
Classifier: Operating System :: OS Independent
Classifier: Programming Language :: Python
Classifier: Programming Language :: Python :: 2.7
Classifier: Topic :: Internet :: WWW/HTTP
Classifier: Topic :: Internet :: WWW/HTTP :: Dynamic Content
Classifier: Topic :: Software Development :: Libraries :: Python Modules
